csan/__init__.py
csan/cutter.py
csan/main.py
csan/naming.py
csan/py.typed
csan/table.py
csan-0.4.2.dist-info/WHEEL
csan-0.4.2.dist-info/entry_points.txt
csan-0.4.2.dist-info/METADATA
csan-0.4.2.dist-info/RECORD
