Metadata-Version: 2.4
Name: csan
Version: 0.4.2
Summary: Generate a Cutter-Sanborn call number. Can be used as CLI tool or Python library.
Keywords: cutter,sanborn,cutter-sanborn,cutter-number,cutter-call-number,cutter-notation,catalog,catalogue,cataloging,cataloguing,library,library-catalog,call-number,three-figure,bibliographic,cli,command-line
Author: VERA LVX
Author-email: VERA LVX <veralvx@veralvx.com>
License-Expression: Apache-2.0
Classifier: Development Status :: 4 - Beta
Classifier: Environment :: Console
Classifier: Intended Audience :: Developers
Classifier: Intended Audience :: Information Technology
Classifier: License :: OSI Approved :: Apache Software License
Classifier: Natural Language :: English
Classifier: Operating System :: OS Independent
Classifier: Programming Language :: Python :: 3
Classifier: Programming Language :: Python :: 3 :: Only
Classifier: Programming Language :: Python :: 3.10
Classifier: Programming Language :: Python :: 3.11
Classifier: Programming Language :: Python :: 3.12
Classifier: Programming Language :: Python :: 3.13
Classifier: Programming Language :: Python :: 3.14
Classifier: Topic :: Software Development :: Libraries
Classifier: Topic :: Software Development :: Libraries :: Python Modules
Classifier: Topic :: Text Processing
Classifier: Topic :: Text Processing :: General
Classifier: Topic :: Text Processing :: Indexing
Classifier: Topic :: Utilities
Classifier: Typing :: Typed
Maintainer: VERA LVX
Maintainer-email: VERA LVX <veralvx@veralvx.com>
Requires-Python: >=3.10
Project-URL: Changelog, https://github.com/veralvx/csan/blob/main/CHANGELOG.md
Project-URL: Documentation, https://github.com/veralvx/csan
Project-URL: Homepage, https://github.com/veralvx/csan
Project-URL: Issues, https://github.com/veralvx/csan/issues
Project-URL: Releasenotes, https://github.com/veralvx/csan/releases
Project-URL: Repository, https://github.com/veralvx/csan
